word_distance_asz/__init__.py
word_distance_asz/distance.py
word_distance_asz-0.1.14.dist-info/LICENSE
word_distance_asz-0.1.14.dist-info/METADATA
word_distance_asz-0.1.14.dist-info/WHEEL
word_distance_asz-0.1.14.dist-info/top_level.txt
word_distance_asz-0.1.14.dist-info/RECORD
