Metadata-Version: 2.1
Name: word-distance-asz
Version: 0.1.14
Summary: word distance
Home-page: UNKNOWN
Author: ArizonaS
Author-email: 
License: UNKNOWN
Platform: UNKNOWN
Classifier: Programming Language :: Python :: 3
Classifier: License :: OSI Approved :: MIT License
Classifier: Operating System :: OS Independent
